huaweicloudsdktesthub/__init__.py
huaweicloudsdktesthub/v1/__init__.py
huaweicloudsdktesthub/v1/cloudtest_async_client.py
huaweicloudsdktesthub/v1/cloudtest_client.py
huaweicloudsdktesthub/v1/model/__init__.py
huaweicloudsdktesthub/v1/model/assigned_user_info.py
huaweicloudsdktesthub/v1/model/batch_delete_test_case_request.py
huaweicloudsdktesthub/v1/model/batch_delete_test_case_request_body.py
huaweicloudsdktesthub/v1/model/batch_delete_test_case_response.py
huaweicloudsdktesthub/v1/model/create_plan_request.py
huaweicloudsdktesthub/v1/model/create_plan_request_body.py
huaweicloudsdktesthub/v1/model/create_plan_response.py
huaweicloudsdktesthub/v1/model/create_service_request.py
huaweicloudsdktesthub/v1/model/create_service_response.py
huaweicloudsdktesthub/v1/model/create_test_case_in_plan_request.py
huaweicloudsdktesthub/v1/model/create_test_case_in_plan_request_body.py
huaweicloudsdktesthub/v1/model/create_test_case_in_plan_response.py
huaweicloudsdktesthub/v1/model/create_test_case_request.py
huaweicloudsdktesthub/v1/model/create_test_case_request_body.py
huaweicloudsdktesthub/v1/model/create_test_case_response.py
huaweicloudsdktesthub/v1/model/delete_service_request.py
huaweicloudsdktesthub/v1/model/delete_service_response.py
huaweicloudsdktesthub/v1/model/error_case_info_bean.py
huaweicloudsdktesthub/v1/model/error_detail_info.py
huaweicloudsdktesthub/v1/model/extend_author_info.py
huaweicloudsdktesthub/v1/model/extend_info.py
huaweicloudsdktesthub/v1/model/external_service_biz_case.py
huaweicloudsdktesthub/v1/model/external_service_case_info.py
huaweicloudsdktesthub/v1/model/external_service_case_step.py
huaweicloudsdktesthub/v1/model/plan_cycle.py
huaweicloudsdktesthub/v1/model/run_test_case_request.py
huaweicloudsdktesthub/v1/model/run_test_case_request_body.py
huaweicloudsdktesthub/v1/model/run_test_case_response.py
huaweicloudsdktesthub/v1/model/service_request_body.py
huaweicloudsdktesthub/v1/model/services_info.py
huaweicloudsdktesthub-3.0.13b0.dist-info/LICENSE
huaweicloudsdktesthub-3.0.13b0.dist-info/METADATA
huaweicloudsdktesthub-3.0.13b0.dist-info/WHEEL
huaweicloudsdktesthub-3.0.13b0.dist-info/top_level.txt
huaweicloudsdktesthub-3.0.13b0.dist-info/RECORD
