Metadata-Version: 2.1
Name: huaweicloudsdktesthub
Version: 3.0.13b0
Summary: cloudtest
Home-page: https://github.com/huaweicloud/huaweicloud-sdk-python-v3
Author: HuaweiCloud SDK
Author-email: hwcloudsdk@huawei.com
License: Apache LICENSE 2.0
Keywords: huaweicloud,sdk,cloudtest
Platform: UNKNOWN
Classifier: Development Status :: 5 - Production/Stable
Classifier: Intended Audience :: Developers
Classifier: License :: OSI Approved :: Apache Software License
Classifier: Programming Language :: Python :: 3
Classifier: Programming Language :: Python :: 3.3
Classifier: Programming Language :: Python :: 3.4
Classifier: Programming Language :: Python :: 3.5
Classifier: Programming Language :: Python :: 3.6
Classifier: Programming Language :: Python :: 3.7
Classifier: Topic :: Software Development
Requires-Dist: huaweicloudsdkcore
